endex_factset_api/__init__.py
endex_factset_api/_base_client.py
endex_factset_api/_client.py
endex_factset_api/_compat.py
endex_factset_api/_constants.py
endex_factset_api/_exceptions.py
endex_factset_api/_files.py
endex_factset_api/_models.py
endex_factset_api/_qs.py
endex_factset_api/_resource.py
endex_factset_api/_response.py
endex_factset_api/_streaming.py
endex_factset_api/_types.py
endex_factset_api/_version.py
endex_factset_api/py.typed
endex_factset_api/_utils/__init__.py
endex_factset_api/_utils/_logs.py
endex_factset_api/_utils/_proxy.py
endex_factset_api/_utils/_reflection.py
endex_factset_api/_utils/_streams.py
endex_factset_api/_utils/_sync.py
endex_factset_api/_utils/_transform.py
endex_factset_api/_utils/_typing.py
endex_factset_api/_utils/_utils.py
endex_factset_api/lib/.keep
endex_factset_api/resources/__init__.py
endex_factset_api/resources/fact_set_fundamentals.py
endex_factset_api/resources/metrics.py
endex_factset_api/resources/segments.py
endex_factset_api/resources/batch_processing/__init__.py
endex_factset_api/resources/batch_processing/batch_processing.py
endex_factset_api/resources/batch_processing/batch_result.py
endex_factset_api/resources/batch_processing/batch_status.py
endex_factset_api/resources/company_reports/__init__.py
endex_factset_api/resources/company_reports/company_reports.py
endex_factset_api/resources/company_reports/financial_statement.py
endex_factset_api/resources/company_reports/fundamentals.py
endex_factset_api/resources/company_reports/profile.py
endex_factset_api/types/__init__.py
endex_factset_api/types/fact_set_fundamental_create_params.py
endex_factset_api/types/fact_set_fundamental_list_params.py
endex_factset_api/types/fundamentals_response.py
endex_factset_api/types/metric_list_params.py
endex_factset_api/types/metrics_response.py
endex_factset_api/types/segment_create_params.py
endex_factset_api/types/segment_list_params.py
endex_factset_api/types/segments_response.py
endex_factset_api-0.1.0a3.dist-info/METADATA
endex_factset_api-0.1.0a3.dist-info/WHEEL
endex_factset_api-0.1.0a3.dist-info/licenses/LICENSE
endex_factset_api-0.1.0a3.dist-info/RECORD
